{
  "task_id": "20250122-xingkey-tarot-mvp",
  "started_at": "2025-01-22",
  "completed_at": "2025-01-22",
  "current_phase": "COMPLETE",
  "phases": {
    "Task 1": "completed",
    "Task 2": "completed",
    "Task 3": "completed",
    "Task 4": "completed",
    "Task 5": "completed",
    "Task 6": "completed",
    "Task 7": "completed",
    "Task 8": "completed",
    "Task 9": "completed",
    "Task 10": "completed",
    "Task 11": "completed",
    "Task 12": "completed"
  },
  "completed": ["Task 1", "Task 2", "Task 3", "Task 4", "Task 5", "Task 6", "Task 7", "Task 8", "Task 9", "Task 10", "Task 11", "Task 12"],
  "iterations": 12,
  "stale_count": 0,
  "summary": {
    "total_files": 54,
    "arkts_files": 36,
    "json_files": 15,
    "ts_files": 2,
    "test_files": 5,
    "cards": 78,
    "interpretations": 78,
    "compliance_locations": ["Index.ets modal", "DivinationResultPage footer", "SharePreview constant"],
    "audit_checks_passed": 8,
    "audit_checks_failed": 0
  }
}
